pytest_case_provider/__init__.py
pytest_case_provider/abc.py
pytest_case_provider/case/__init__.py
pytest_case_provider/case/abc.py
pytest_case_provider/case/collector.py
pytest_case_provider/case/configure.py
pytest_case_provider/case/container.py
pytest_case_provider/case/decorator.py
pytest_case_provider/case/generator.py
pytest_case_provider/case/info.py
pytest_case_provider/case/provider.py
pytest_case_provider/case/storage.py
pytest_case_provider/fixture.py
pytest_case_provider/inspect.py
pytest_case_provider/mark.py
pytest_case_provider/plugin.py
pytest_case_provider/py.typed
pytest_case_provider-0.4.3.dist-info/METADATA
pytest_case_provider-0.4.3.dist-info/WHEEL
pytest_case_provider-0.4.3.dist-info/entry_points.txt
pytest_case_provider-0.4.3.dist-info/licenses/LICENSE
pytest_case_provider-0.4.3.dist-info/RECORD
