Metadata-Version: 2.4
Name: pytest-case-provider
Version: 0.4.3
Summary: Advanced pytest parametrization plugin that generates test case instances from sync or async factories.
License: MIT
License-File: LICENSE
Keywords: pytest,parametrize,test,case,testcase,decorator
Author: zerlok
Author-email: danil.troshnev@gmail.com
Requires-Python: >=3.9,<4.0
Classifier: Development Status :: 3 - Alpha
Classifier: Framework :: Pytest
Classifier: Intended Audience :: Developers
Classifier: License :: OSI Approved :: MIT License
Classifier: Operating System :: OS Independent
Classifier: Programming Language :: Python :: 3
Classifier: Programming Language :: Python :: 3.9
Classifier: Programming Language :: Python :: 3.10
Classifier: Programming Language :: Python :: 3.11
Classifier: Programming Language :: Python :: 3.12
Classifier: Programming Language :: Python :: 3.13
Classifier: Programming Language :: Python :: 3.14
Classifier: Topic :: Software Development :: Libraries
Classifier: Topic :: Software Development :: Testing
Classifier: Typing :: Typed
Requires-Dist: pytest (>=8)
Requires-Dist: typing-extensions (>=4,<5)
Project-URL: Homepage, https://github.com/zerlok/pytest-case-provider
Project-URL: Issues, https://github.com/zerlok/pytest-case-provider/issues
